setup.py
buildorchestra/__init__.py
buildorchestra/build.py
buildorchestra/result.py
buildorchestra/steps.py
buildorchestra.egg-info/PKG-INFO
buildorchestra.egg-info/SOURCES.txt
buildorchestra.egg-info/dependency_links.txt
buildorchestra.egg-info/requires.txt
buildorchestra.egg-info/top_level.txt