Metadata-Version: 1.0
Name: buildorchestra
Version: 0.1.4
Summary: Build system orchestration tool
Home-page: http://github.com/Gohla/buildorchestra
Author: Gabriel Konat
Author-email: g.d.p.konat@tudelft.nl
License: Apache 2.0
Platform: UNKNOWN
